rs_datasets/__init__.py
rs_datasets/amazon.py
rs_datasets/anime.py
rs_datasets/book_crossing.py
rs_datasets/dating_agency.py
rs_datasets/diginetica.py
rs_datasets/epinions.py
rs_datasets/generic_dataset.py
rs_datasets/goodreads.py
rs_datasets/in_progress.py
rs_datasets/jester.py
rs_datasets/lastfm.py
rs_datasets/movielens.py
rs_datasets/msd.py
rs_datasets/netflix.py
rs_datasets/rekko.py
rs_datasets/retail_rocket.py
rs_datasets/steam.py
rs_datasets/yoochoose.py
rs_datasets/youchoose.py
rs_datasets/data_loader/__init__.py
rs_datasets/data_loader/archives.py
rs_datasets/data_loader/loaders.py
rs_datasets-0.5.1.dist-info/METADATA
rs_datasets-0.5.1.dist-info/WHEEL
rs_datasets-0.5.1.dist-info/top_level.txt
rs_datasets-0.5.1.dist-info/RECORD
