Metadata-Version: 2.1
Name: rs-datasets
Version: 0.5.1
Summary: Tool for autodownloading recommendation systems datasets
Home-page: https://github.com/Darel13712/rs_datasets
Author: Yan-Martin Tamm
Author-email: darel142857@gmail.com
License: UNKNOWN
Platform: UNKNOWN
Classifier: Programming Language :: Python :: 3
Classifier: License :: OSI Approved :: MIT License
Classifier: Operating System :: OS Independent
Requires-Python: >=3.6
Requires-Dist: datatable
Requires-Dist: pandas
Requires-Dist: gdown
Requires-Dist: pyarrow
Requires-Dist: tqdm
Requires-Dist: xlrd
Requires-Dist: kaggle
Requires-Dist: py7zr
Requires-Dist: openpyxl
